LICENSE.txt
README.md
setup.cfg
setup.py
pltEditorTool/__init__.py
pltEditorTool/icon2.png
pltEditorTool/plot_code.py
pltEditorTool/plot_functions.py
pltEditorTool/pltEditorGUI-1.ui
pltEditorTool/pltEditorGUI-2.ui
pltEditorTool/pltEditorTool.py
pltEditorTool/util.py
pltEditorTool.egg-info/PKG-INFO
pltEditorTool.egg-info/SOURCES.txt
pltEditorTool.egg-info/dependency_links.txt
pltEditorTool.egg-info/requires.txt
pltEditorTool.egg-info/top_level.txt