Metadata-Version: 2.1
Name: pltEditorTool
Version: 3.1.1
Summary: This package provides a GUI for editing matplotlib plots
Home-page: https://github.com/RichardCouperthwaite/plt-editor-tool
Author: Richard Couperthwaite
Author-email: richard.couperthwaite@gmail.com
License: GNU Lesser General Public License v3 (LGPLv3)
Download-URL: https://github.com/RichardCouperthwaite/plt-editor-tool/archive/refs/tags/3.1.1.tar.gz
Keywords: Matplotlib,Pyplot,GUI,Editor
Platform: UNKNOWN
Classifier: Development Status :: 5 - Production/Stable
Classifier: Intended Audience :: Developers
Classifier: Topic :: Software Development :: Build Tools
Classifier: License :: OSI Approved :: GNU Lesser General Public License v3 (LGPLv3)
Classifier: Programming Language :: Python :: 3
Classifier: Programming Language :: Python :: 3.4
Classifier: Programming Language :: Python :: 3.5
Classifier: Programming Language :: Python :: 3.6
License-File: LICENSE.txt
